eazyml_counterfactual/__init__.py
eazyml_counterfactual/Linux_x86_64/__init__.py
eazyml_counterfactual/Linux_x86_64/eazyml_counterfactual/__init__.cpython-310-x86_64-linux-gnu.so
eazyml_counterfactual/Linux_x86_64/eazyml_counterfactual/__init__.cpython-311-x86_64-linux-gnu.so
eazyml_counterfactual/Linux_x86_64/eazyml_counterfactual/__init__.cpython-312-x86_64-linux-gnu.so
eazyml_counterfactual/Linux_x86_64/eazyml_counterfactual/__init__.cpython-38-x86_64-linux-gnu.so
eazyml_counterfactual/Linux_x86_64/eazyml_counterfactual/__init__.cpython-39-x86_64-linux-gnu.so
eazyml_counterfactual/Linux_x86_64/eazyml_counterfactual/client.cpython-310-x86_64-linux-gnu.so
eazyml_counterfactual/Linux_x86_64/eazyml_counterfactual/client.cpython-311-x86_64-linux-gnu.so
eazyml_counterfactual/Linux_x86_64/eazyml_counterfactual/client.cpython-312-x86_64-linux-gnu.so
eazyml_counterfactual/Linux_x86_64/eazyml_counterfactual/client.cpython-38-x86_64-linux-gnu.so
eazyml_counterfactual/Linux_x86_64/eazyml_counterfactual/client.cpython-39-x86_64-linux-gnu.so
eazyml_counterfactual/Linux_x86_64/eazyml_counterfactual/globals/__init__.cpython-310-x86_64-linux-gnu.so
eazyml_counterfactual/Linux_x86_64/eazyml_counterfactual/globals/__init__.cpython-311-x86_64-linux-gnu.so
eazyml_counterfactual/Linux_x86_64/eazyml_counterfactual/globals/__init__.cpython-312-x86_64-linux-gnu.so
eazyml_counterfactual/Linux_x86_64/eazyml_counterfactual/globals/__init__.cpython-38-x86_64-linux-gnu.so
eazyml_counterfactual/Linux_x86_64/eazyml_counterfactual/globals/__init__.cpython-39-x86_64-linux-gnu.so
eazyml_counterfactual/Linux_x86_64/eazyml_counterfactual/globals/config.cpython-310-x86_64-linux-gnu.so
eazyml_counterfactual/Linux_x86_64/eazyml_counterfactual/globals/config.cpython-311-x86_64-linux-gnu.so
eazyml_counterfactual/Linux_x86_64/eazyml_counterfactual/globals/config.cpython-312-x86_64-linux-gnu.so
eazyml_counterfactual/Linux_x86_64/eazyml_counterfactual/globals/config.cpython-38-x86_64-linux-gnu.so
eazyml_counterfactual-1.0.3.dist-info/LICENSE
eazyml_counterfactual-1.0.3.dist-info/METADATA
eazyml_counterfactual-1.0.3.dist-info/WHEEL
eazyml_counterfactual-1.0.3.dist-info/top_level.txt
eazyml_counterfactual-1.0.3.dist-info/RECORD
