Metadata-Version: 2.1
Name: eazyml-counterfactual
Version: 1.0.3
Summary: eazyml-counterfactual from EazyML family for counterfactual explanations, prescriptive analytics, and actionable insights to optimize predictive outcomes.
Home-page: https://eazyml.com/
Author: EazyML
Author-email: admin@eazyml.com
Project-URL: Documentation, https://docs.eazyml.com/
Project-URL: Homepage, https://eazyml.com/
Project-URL: Contact Us, https://eazyml.com/trust-in-ai
Project-URL: eazyml-automl, https://pypi.org/project/eazyml-automl/
Project-URL: eazyml-counterfactual, https://pypi.org/project/eazyml-counterfactual/
Project-URL: eazyml-xai, https://pypi.org/project/eazyml-xai/
Project-URL: eazyml-xai-image, https://pypi.org/project/eazyml-xai-image/
Project-URL: eazyml-insight, https://pypi.org/project/eazyml-insight/
Project-URL: eazyml-data-quality, https://pypi.org/project/eazyml-data-quality/
Keywords: counterfactuals,prescriptive-analytics,optimal-decision,what-if-analysis,actionable-insights,prediction-optimization,causal-inference,machine-learning,ml-api,explainable-ai
Classifier: Development Status :: 5 - Production/Stable
Classifier: License :: Other/Proprietary License
Classifier: Intended Audience :: Education
Classifier: Intended Audience :: Developers
Classifier: Intended Audience :: Science/Research
Classifier: Intended Audience :: System Administrators
Classifier: Intended Audience :: Information Technology
Classifier: Programming Language :: Python :: 3.8
Classifier: Programming Language :: Python :: 3.9
Classifier: Programming Language :: Python :: 3.10
Classifier: Programming Language :: Python :: 3.11
Classifier: Programming Language :: Python :: 3.12
Classifier: Topic :: Scientific/Engineering :: Artificial Intelligence
Classifier: Operating System :: Unix
Classifier: Operating System :: MacOS
Classifier: Operating System :: Microsoft :: Windows
Classifier: Operating System :: POSIX :: Linux
Requires-Python: >=3.7
License-File: LICENSE
Requires-Dist: openpyxl
Requires-Dist: scipy
Requires-Dist: cryptography
Requires-Dist: pyyaml
Requires-Dist: requests
Requires-Dist: eazyml-automl
Requires-Dist: pandas==1.3.*; python_version <= "3.7"
Requires-Dist: scikit-learn==1.0.*; python_version <= "3.7"
Requires-Dist: pandas>=2.2.3; python_version == "3.10"
Requires-Dist: scikit-learn==1.3.*; python_version == "3.10"
Requires-Dist: pandas>=2.2.3; python_version == "3.11"
Requires-Dist: scikit-learn==1.3.*; python_version == "3.11"
Requires-Dist: pandas>=2.0.3; python_version == "3.8"
Requires-Dist: scikit-learn==1.3.*; python_version == "3.8"
Requires-Dist: pandas>=2.2.3; python_version == "3.9"
Requires-Dist: scikit-learn==1.3.*; python_version == "3.9"
Requires-Dist: pandas>=2.2.3; python_version > "3.11"
Requires-Dist: scikit-learn==1.3.*; python_version > "3.11"
